{
  "appName": "app2",
  "appVersion": "0.5.0",
  "generationTimestamp": "2025-05-26T20:30:19.885893",
  "generator": "Python IaC Script",
  "uniqueId": "2885a29f-2822-4666-bfe3-8d3aadb48bab",
  "parametersReceived": {
    "app_name": "app2",
    "input_data": "datos_adicionales_para_python",
    "q1": "v1",
    "q10": "v10",
    "q11": "v11",
    "q12": "v12",
    "q13": "v13",
    "q14": "v14",
    "q15": "v15",
    "q16": "v16",
    "q17": "v17",
    "q18": "v18",
    "q19": "v19",
    "q2": "v2",
    "q20": "v20",
    "q3": "v3",
    "q4": "v4",
    "q5": "v5",
    "q6": "v6",
    "q7": "v7",
    "q8": "v8",
    "q9": "v9",
    "version": "0.5.0"
  },
  "simulatedComplexity": {
    "generated_data_points": [
      "Simulated data point 0 for app2 v0.5.0 - f999e934-f566-478e-aaa3-40f0b7ef1a5b",
      "Simulated data point 1 for app2 v0.5.0 - c79bcc09-eadc-410b-995a-00f388b4b6da",
      "Simulated data point 2 for app2 v0.5.0 - 6a449c25-c3bc-4ed1-a4ed-fafeb9e9f46a",
      "Simulated data point 3 for app2 v0.5.0 - 68df0e1f-af4a-4eee-a078-fd95029c7d4b",
      "Simulated data point 4 for app2 v0.5.0 - 6d950ab4-467e-48a8-96fb-71a2804024bd",
      "Simulated data point 5 for app2 v0.5.0 - e26aa5b2-ea33-4b23-8f7e-dd320d0f3e13",
      "Simulated data point 6 for app2 v0.5.0 - d736e734-61e5-4948-9504-a42e528344ac",
      "Simulated data point 7 for app2 v0.5.0 - d2ca95c3-b2ee-4239-9ecf-4fb856410cf1",
      "Simulated data point 8 for app2 v0.5.0 - e1de2095-91eb-46e3-a1b7-e327e76969ff",
      "Simulated data point 9 for app2 v0.5.0 - 3003ada4-e229-4cec-8a55-9b731249d6c9",
      "Simulated data point 10 for app2 v0.5.0 - b5308a6a-4959-4172-adfd-63076011e215",
      "Simulated data point 11 for app2 v0.5.0 - 759a18c3-1244-4150-bac3-15111a6296f6",
      "Simulated data point 12 for app2 v0.5.0 - b67d1fd1-8fad-4ee6-ad05-a159867d43b1",
      "Simulated data point 13 for app2 v0.5.0 - d82bf355-e944-4b5a-abc4-1311e853ec2c",
      "Simulated data point 14 for app2 v0.5.0 - 62e9e161-f808-4d79-bc54-5dccca0e3a67"
    ],
    "simulated_dependencies": {
      "dep_0": "version_0.1",
      "dep_1": "version_1.2",
      "dep_2": "version_2.3",
      "dep_3": "version_3.4",
      "dep_4": "version_4.5",
      "dep_5": "version_5.6",
      "dep_6": "version_6.7",
      "dep_7": "version_7.8",
      "dep_8": "version_8.9",
      "dep_9": "version_9.10"
    },
    "calculated_metrics": {
      "val_0": 0.0,
      "val_1": 66.66666666666667,
      "val_2": 80.0,
      "val_3": 85.71428571428571,
      "val_4": 88.88888888888889,
      "val_5": 90.9090909090909,
      "val_6": 92.3076923076923,
      "val_7": 93.33333333333333,
      "val_8": 94.11764705882354,
      "val_9": 94.73684210526316
    },
    "generation_details": [
      "Detail line 0",
      "Detail line 1",
      "Detail line 2",
      "Detail line 3",
      "Detail line 4",
      "Detail line 5",
      "Detail line 6",
      "Detail line 7",
      "Detail line 8",
      "Detail line 9",
      "Detail line 10",
      "Detail line 11",
      "Detail line 12",
      "Detail line 13",
      "Detail line 14"
    ]
  },
  "additional_info": [
    "Linea info 0",
    "Linea info 1",
    "Linea info 2",
    "Linea info 3",
    "Linea info 4",
    "Linea info 5",
    "Linea info 6",
    "Linea info 7",
    "Linea info 8",
    "Linea info 9"
  ],
  "status_flags": {
    "flag_0": true,
    "flag_1": false,
    "flag_2": true,
    "flag_3": false,
    "flag_4": true,
    "flag_5": false,
    "flag_6": true,
    "flag_7": false,
    "flag_8": true,
    "flag_9": false
  },
  "processing_log": [
    "Entrada log  0: Item procesado 1a3e5299-625a-4963-9c66-090a52bbe269",
    "Entrada log  1: Item procesado ba43e765-5fde-4847-ae7b-d4bc2c7d3364",
    "Entrada log  2: Item procesado c82ede34-2bd7-4be6-b4da-13cabff1bd28",
    "Entrada log  3: Item procesado d3c12b7d-203b-402c-be72-5ffc748daae1",
    "Entrada log  4: Item procesado 6c1eb2f4-3b33-4663-96a9-2342fbd20e50",
    "Entrada log  5: Item procesado 4cbee9fe-3325-4e23-9706-d3da29a43d51",
    "Entrada log  6: Item procesado 9aa0e9d9-fa7b-4db0-8cdc-94b4fc92d24d",
    "Entrada log  7: Item procesado 10c1b1cf-f3ad-4a49-8c9e-38e771f4149e",
    "Entrada log  8: Item procesado 54aad8ef-4f0f-42a9-b5bf-87f8a4438fb2",
    "Entrada log  9: Item procesado 85211576-35c0-4db8-8d30-7155ba7db035",
    "Entrada log  10: Item procesado d0805a0c-7316-44e1-85a1-cf6efdde9b0f",
    "Entrada log  11: Item procesado c8078ad5-ee37-4b7b-a9a2-fa11c0b3868a",
    "Entrada log  12: Item procesado c0bd5072-cd7a-4c1c-94c2-3def770c50c4",
    "Entrada log  13: Item procesado 69de8560-4ead-4dbd-a20c-7a5af01b3929",
    "Entrada log  14: Item procesado 52a9d593-20fe-4e52-ab7b-2f0f98476a22",
    "Entrada log  15: Item procesado 5399b1ee-34d0-45ae-bfa7-864feca73de4",
    "Entrada log  16: Item procesado ea581a8f-c17c-46cb-a0d9-e25a637089cf",
    "Entrada log  17: Item procesado a688a39c-b25b-4b4d-8fd7-3fdf8fbf762c",
    "Entrada log  18: Item procesado 57fc2676-0fad-4812-97e0-940a0e94f1d8",
    "Entrada log  19: Item procesado 9f46e4ae-94c4-4919-ba9d-9025bc136a46",
    "Entrada log  20: Item procesado 5961e9d7-73b8-4b72-bc58-71508bc4a4b3",
    "Entrada log  21: Item procesado 645fcbae-ddfb-48d8-b88a-6dbbae2a598c",
    "Entrada log  22: Item procesado 81c71883-65d4-4a22-8cfe-7c40ea181b6e",
    "Entrada log  23: Item procesado 429c2a48-565b-4394-9ea1-63f752f12ac8",
    "Entrada log  24: Item procesado 81d35be4-e6b5-463c-b47d-cf86f1e453f0",
    "Entrada log  25: Item procesado f8d1fade-827f-4728-be4c-8e52b9ec18a0",
    "Entrada log  26: Item procesado 9ce4976f-576e-4933-a2bd-711e527327c6",
    "Entrada log  27: Item procesado f502799a-6108-4d04-96ca-db47c3792018",
    "Entrada log  28: Item procesado 4cbfe6b9-e7f8-4387-a772-720c389e944e",
    "Entrada log  29: Item procesado e08f1e02-522e-4f75-9b43-e80f5e2c56ab"
  ]
}